beekeeper/__init__.py
beekeeper/__version__.py
beekeeper/admin.py
beekeeper/apps.py
beekeeper/models.py
beekeeper/tests.py
beekeeper/views.py
beekeeper/migrations/__init__.py
django_beekeeper-0.0.0.dist-info/LICENSE.txt
django_beekeeper-0.0.0.dist-info/METADATA
django_beekeeper-0.0.0.dist-info/WHEEL
django_beekeeper-0.0.0.dist-info/top_level.txt
django_beekeeper-0.0.0.dist-info/RECORD
