Metadata-Version: 2.1
Name: django-beekeeper
Version: 0.0.0
Summary: Django Beekeeper is a module for make Api Rest with OpenApi documentation
Home-page: https://github.com/fundor333/Beekeeper
Author: Matteo Scarpa
Author-email: fundor333@fundor333.com
License: MIT License
Platform: UNKNOWN
Classifier: License :: OSI Approved :: MIT License
Classifier: Programming Language :: Python
Classifier: Programming Language :: Python :: 3
Classifier: Programming Language :: Python :: 3.5
Classifier: Programming Language :: Python :: 3.6
Classifier: Programming Language :: Python :: 3.7
Classifier: Programming Language :: Python :: 3.8
Classifier: Programming Language :: Python :: Implementation :: CPython
Classifier: Programming Language :: Python :: Implementation :: PyPy
Requires-Python: >=3.5.0
Requires-Dist: Django (>=3.0)
